{ "Accionista-uvwmhskzgnd2zdeew2jrdsxo5q-staging": [{ "PutRequest": { "Item": { "id": { "S": "37654"},"tipoIdentificacion":{"S":"Cédula"},"identificacion":{"S":"1701756171"},"nombre":{"S":"REA CASTILLO FAUSTO EDMUNDO-HEREDEROS"},"tipoPersona":{"S":"PN"},"estado":{"S":"Activo"},"paisNacionalidad":{"S":"ECUATORIANA"},"tipoAcciones":{"S":"M"},"cantidadAcciones":{"N":"813" } } } },
{ "PutRequest": { "Item": { "id": { "S": "37766"},"tipoIdentificacion":{"S":"Cédula"},"identificacion":{"S":"1708094337"},"nombre":{"S":"REYES LUGO SILVIA DEL PILAR"},"tipoPersona":{"S":"PN"},"estado":{"S":"Activo"},"paisNacionalidad":{"S":"ECUATORIANA"},"tipoAcciones":{"S":"D"},"cantidadAcciones":{"N":"231" } } } },
{ "PutRequest": { "Item": { "id": { "S": "37889"},"tipoIdentificacion":{"S":"Cédula"},"identificacion":{"S":"1701942268"},"nombre":{"S":"REYES RUIZ ALBERTO OSWALDO"},"tipoPersona":{"S":"PN"},"estado":{"S":"Activo"},"paisNacionalidad":{"S":"ECUATORIANA"},"tipoAcciones":{"S":"D"},"cantidadAcciones":{"N":"115" } } } },
{ "PutRequest": { "Item": { "id": { "S": "37914"},"tipoIdentificacion":{"S":"Cédula"},"identificacion":{"S":"1701980474"},"nombre":{"S":"RIVADENEIRA GARCIA SANTIAGO PATRICIO"},"tipoPersona":{"S":"PN"},"estado":{"S":"Inactivo"},"paisNacionalidad":{"S":"ECUATORIANA"},"tipoAcciones":{"S":"D"},"cantidadAcciones":{"N":"0" } } } },
{ "PutRequest": { "Item": { "id": { "S": "37739"},"tipoIdentificacion":{"S":"Cédula"},"identificacion":{"S":"1701529966"},"nombre":{"S":"RIVADENIERA JARRIN MAGDALENA MARIA DEL PILAR"},"tipoPersona":{"S":"PN"},"estado":{"S":"Activo"},"paisNacionalidad":{"S":"ECUATORIANA"},"tipoAcciones":{"S":"D"},"cantidadAcciones":{"N":"286" } } } },
{ "PutRequest": { "Item": { "id": { "S": "60079"},"tipoIdentificacion":{"S":"Cédula"},"identificacion":{"S":"909306227"},"nombre":{"S":"RIVAS CHAVEZ FANNY MARIA FATIMA"},"tipoPersona":{"S":"PN"},"estado":{"S":"Activo"},"paisNacionalidad":{"S":"ECUATORIANA"},"tipoAcciones":{"S":"D"},"cantidadAcciones":{"N":"1026" } } } },
{ "PutRequest": { "Item": { "id": { "S": "60078"},"tipoIdentificacion":{"S":"Cédula"},"identificacion":{"S":"1704642782"},"nombre":{"S":"RIVAS HIDALGO HILDA SORAYA"},"tipoPersona":{"S":"PN"},"estado":{"S":"Activo"},"paisNacionalidad":{"S":"ECUATORIANA"},"tipoAcciones":{"S":"D"},"cantidadAcciones":{"N":"2026" } } } },
{ "PutRequest": { "Item": { "id": { "S": "37590"},"tipoIdentificacion":{"S":"Cédula"},"identificacion":{"S":"1704641818"},"nombre":{"S":"RIVAS HIDALGO NANCY JEANNETTE"},"tipoPersona":{"S":"PN"},"estado":{"S":"Inactivo"},"paisNacionalidad":{"S":"ECUATORIANA"},"tipoAcciones":{"S":"D"},"cantidadAcciones":{"N":"0" } } } },
{ "PutRequest": { "Item": { "id": { "S": "37767"},"tipoIdentificacion":{"S":"Cédula"},"identificacion":{"S":"1701132423"},"nombre":{"S":"RIVERA CADENA ABDON MESIAS"},"tipoPersona":{"S":"PN"},"estado":{"S":"Inactivo"},"paisNacionalidad":{"S":"ECUATORIANA"},"tipoAcciones":{"S":"D"},"cantidadAcciones":{"N":"0" } } } },
{ "PutRequest": { "Item": { "id": { "S": "37819"},"tipoIdentificacion":{"S":"Cédula"},"identificacion":{"S":"1701579649"},"nombre":{"S":"RIVERA FLORES JORGE EDUARDO"},"tipoPersona":{"S":"PN"},"estado":{"S":"Inactivo"},"paisNacionalidad":{"S":"ECUATORIANA"},"tipoAcciones":{"S":"D"},"cantidadAcciones":{"N":"0" } } } },
{ "PutRequest": { "Item": { "id": { "S": "37909"},"tipoIdentificacion":{"S":"Cédula"},"identificacion":{"S":"1702156009"},"nombre":{"S":"ROBAYO MONTERO JESUS RENE"},"tipoPersona":{"S":"PN"},"estado":{"S":"Inactivo"},"paisNacionalidad":{"S":"ECUATORIANA"},"tipoAcciones":{"S":"D"},"cantidadAcciones":{"N":"0" } } } },
{ "PutRequest": { "Item": { "id": { "S": "37803"},"tipoIdentificacion":{"S":"Cédula"},"identificacion":{"S":"1001222114"},"nombre":{"S":"RODRIGUEZ DE LA TORRE CARMEN EUGENIA"},"tipoPersona":{"S":"PN"},"estado":{"S":"Inactivo"},"paisNacionalidad":{"S":"ECUATORIANA"},"tipoAcciones":{"S":"D"},"cantidadAcciones":{"N":"0" } } } },
{ "PutRequest": { "Item": { "id": { "S": "14017"},"tipoIdentificacion":{"S":"Cédula"},"identificacion":{"S":"1700612144"},"nombre":{"S":"RODRIGUEZ GOMEZ GLORIA ESPERANZA"},"tipoPersona":{"S":"PN"},"estado":{"S":"Inactivo"},"paisNacionalidad":{"S":"ECUATORIANA"},"tipoAcciones":{"S":"M"},"cantidadAcciones":{"N":"0" } } } },
{ "PutRequest": { "Item": { "id": { "S": "37923"},"tipoIdentificacion":{"S":"Cédula"},"identificacion":{"S":"1701852012"},"nombre":{"S":"RODRIGUEZ MARTINEZ RUTH DE LAS MERCEDES"},"tipoPersona":{"S":"PN"},"estado":{"S":"Activo"},"paisNacionalidad":{"S":"ECUATORIANA"},"tipoAcciones":{"S":"M"},"cantidadAcciones":{"N":"93" } } } },
{ "PutRequest": { "Item": { "id": { "S": "23108"},"tipoIdentificacion":{"S":"Cédula"},"identificacion":{"S":"916482276"},"nombre":{"S":"RODRIGUEZ SORNOZA MIKE DAVIS"},"tipoPersona":{"S":"PN"},"estado":{"S":"Activo"},"paisNacionalidad":{"S":"ECUATORIANA"},"tipoAcciones":{"S":"D"},"cantidadAcciones":{"N":"170" } } } },
{ "PutRequest": { "Item": { "id": { "S": "37591"},"tipoIdentificacion":{"S":"Cédula"},"identificacion":{"S":"1300060553"},"nombre":{"S":"RODRIGUEZ VACA LUIS ARTURO"},"tipoPersona":{"S":"PN"},"estado":{"S":"Inactivo"},"paisNacionalidad":{"S":"ECUATORIANA"},"tipoAcciones":{"S":"D"},"cantidadAcciones":{"N":"0" } } } },
{ "PutRequest": { "Item": { "id": { "S": "37695"},"tipoIdentificacion":{"S":"Cédula"},"identificacion":{"S":"1702199694"},"nombre":{"S":"ROJAS SALAZAR MARCELO GUILLERMO ALBERTO"},"tipoPersona":{"S":"PN"},"estado":{"S":"Activo"},"paisNacionalidad":{"S":"ECUATORIANA"},"tipoAcciones":{"S":"D"},"cantidadAcciones":{"N":"482" } } } },
{ "PutRequest": { "Item": { "id": { "S": "37957"},"tipoIdentificacion":{"S":"Cédula"},"identificacion":{"S":"1701484196"},"nombre":{"S":"ROLDAN VELASCO OLIVIA MARIA"},"tipoPersona":{"S":"PN"},"estado":{"S":"Inactivo"},"paisNacionalidad":{"S":"ECUATORIANA"},"tipoAcciones":{"S":"D"},"cantidadAcciones":{"N":"0" } } } },
{ "PutRequest": { "Item": { "id": { "S": "38014"},"tipoIdentificacion":{"S":"Cédula"},"identificacion":{"S":"1701643577"},"nombre":{"S":"ROMERO ARTETA LUIS EDUARDO DE LA DOLOROSA"},"tipoPersona":{"S":"PN"},"estado":{"S":"Activo"},"paisNacionalidad":{"S":"ECUATORIANA"},"tipoAcciones":{"S":"D"},"cantidadAcciones":{"N":"60" } } } },
{ "PutRequest": { "Item": { "id": { "S": "37890"},"tipoIdentificacion":{"S":"Cédula"},"identificacion":{"S":"1701504753"},"nombre":{"S":"ROMERO JARA ALFREDO IVAN"},"tipoPersona":{"S":"PN"},"estado":{"S":"Activo"},"paisNacionalidad":{"S":"ECUATORIANA"},"tipoAcciones":{"S":"D"},"cantidadAcciones":{"N":"115" } } } },
{ "PutRequest": { "Item": { "id": { "S": "37950"},"tipoIdentificacion":{"S":"Cédula"},"identificacion":{"S":"1703891950"},"nombre":{"S":"ROMO PROANO LUIS MARCELO"},"tipoPersona":{"S":"PN"},"estado":{"S":"Activo"},"paisNacionalidad":{"S":"ECUATORIANA"},"tipoAcciones":{"S":"D"},"cantidadAcciones":{"N":"71" } } } },
{ "PutRequest": { "Item": { "id": { "S": "37823"},"tipoIdentificacion":{"S":"Cédula"},"identificacion":{"S":"1000213387"},"nombre":{"S":"ROSERO AGUIRRE NELSON LUIS ESTANISLAO"},"tipoPersona":{"S":"PN"},"estado":{"S":"Activo"},"paisNacionalidad":{"S":"ECUATORIANA"},"tipoAcciones":{"S":"M"},"cantidadAcciones":{"N":"124" } } } },
{ "PutRequest": { "Item": { "id": { "S": "37846"},"tipoIdentificacion":{"S":"Cédula"},"identificacion":{"S":"1705360970"},"nombre":{"S":"ROSERO ARAUJO CECILIA DEL CARMEN"},"tipoPersona":{"S":"PN"},"estado":{"S":"Activo"},"paisNacionalidad":{"S":"ECUATORIANA"},"tipoAcciones":{"S":"M"},"cantidadAcciones":{"N":"120" } } } },
{ "PutRequest": { "Item": { "id": { "S": "37847"},"tipoIdentificacion":{"S":"Cédula"},"identificacion":{"S":"1704962123"},"nombre":{"S":"ROSERO ARAUJO JEANETTE"},"tipoPersona":{"S":"PN"},"estado":{"S":"Activo"},"paisNacionalidad":{"S":"ECUATORIANA"},"tipoAcciones":{"S":"M"},"cantidadAcciones":{"N":"120" } } } },
{ "PutRequest": { "Item": { "id": { "S": "37848"},"tipoIdentificacion":{"S":"Cédula"},"identificacion":{"S":"1706975487"},"nombre":{"S":"ROSERO ARAUJO LUCIA CARMELINA DEL ROSARIO"},"tipoPersona":{"S":"PN"},"estado":{"S":"Activo"},"paisNacionalidad":{"S":"ECUATORIANA"},"tipoAcciones":{"S":"M"},"cantidadAcciones":{"N":"120" } } } } ] }
