{ "Titulo-uvwmhskzgnd2zdeew2jrdsxo5q-staging": [{ "PutRequest": { "Item": { "id": { "S": "351"},"accionistaID":{"S":"37965"},"titulo":{"S":"406"},"acciones":{"N":"62"},"fechaCompra":{"S":"04-10-2021"},"estado":{"S":"Activo" } } } },
    { "PutRequest": { "Item": { "id": { "S": "352"},"accionistaID":{"S":"37966"},"titulo":{"S":"4"},"acciones":{"N":"60"},"fechaCompra":{"S":"04-10-2021"},"estado":{"S":"Activo" } } } },
    { "PutRequest": { "Item": { "id": { "S": "353"},"accionistaID":{"S":"37967"},"titulo":{"S":"5"},"acciones":{"N":"60"},"fechaCompra":{"S":"04-10-2021"},"estado":{"S":"Activo" } } } },
    { "PutRequest": { "Item": { "id": { "S": "354"},"accionistaID":{"S":"37969"},"titulo":{"S":"24"},"acciones":{"N":"60"},"fechaCompra":{"S":"04-10-2021"},"estado":{"S":"Activo" } } } },
    { "PutRequest": { "Item": { "id": { "S": "355"},"accionistaID":{"S":"42170"},"titulo":{"S":"30"},"acciones":{"N":"60"},"fechaCompra":{"S":"04-10-2021"},"estado":{"S":"Activo" } } } },
    { "PutRequest": { "Item": { "id": { "S": "356"},"accionistaID":{"S":"37971"},"titulo":{"S":"60"},"acciones":{"N":"60"},"fechaCompra":{"S":"04-10-2021"},"estado":{"S":"Activo" } } } },
    { "PutRequest": { "Item": { "id": { "S": "357"},"accionistaID":{"S":"37972"},"titulo":{"S":"62"},"acciones":{"N":"60"},"fechaCompra":{"S":"04-10-2021"},"estado":{"S":"Activo" } } } },
    { "PutRequest": { "Item": { "id": { "S": "358"},"accionistaID":{"S":"37973"},"titulo":{"S":"67"},"acciones":{"N":"60"},"fechaCompra":{"S":"04-10-2021"},"estado":{"S":"Activo" } } } },
    { "PutRequest": { "Item": { "id": { "S": "359"},"accionistaID":{"S":"37974"},"titulo":{"S":"75"},"acciones":{"N":"60"},"fechaCompra":{"S":"04-10-2021"},"estado":{"S":"Activo" } } } },
    { "PutRequest": { "Item": { "id": { "S": "360"},"accionistaID":{"S":"37975"},"titulo":{"S":"77"},"acciones":{"N":"60"},"fechaCompra":{"S":"04-10-2021"},"estado":{"S":"Activo" } } } },
    { "PutRequest": { "Item": { "id": { "S": "361"},"accionistaID":{"S":"37977"},"titulo":{"S":"105"},"acciones":{"N":"60"},"fechaCompra":{"S":"04-10-2021"},"estado":{"S":"Activo" } } } },
    { "PutRequest": { "Item": { "id": { "S": "362"},"accionistaID":{"S":"37978"},"titulo":{"S":"106"},"acciones":{"N":"60"},"fechaCompra":{"S":"04-10-2021"},"estado":{"S":"Activo" } } } },
    { "PutRequest": { "Item": { "id": { "S": "363"},"accionistaID":{"S":"37981"},"titulo":{"S":"189"},"acciones":{"N":"60"},"fechaCompra":{"S":"04-10-2021"},"estado":{"S":"Activo" } } } },
    { "PutRequest": { "Item": { "id": { "S": "364"},"accionistaID":{"S":"42170"},"titulo":{"S":"192"},"acciones":{"N":"60"},"fechaCompra":{"S":"04-10-2021"},"estado":{"S":"Activo" } } } },
    { "PutRequest": { "Item": { "id": { "S": "365"},"accionistaID":{"S":"37983"},"titulo":{"S":"198"},"acciones":{"N":"60"},"fechaCompra":{"S":"04-10-2021"},"estado":{"S":"Activo" } } } },
    { "PutRequest": { "Item": { "id": { "S": "366"},"accionistaID":{"S":"37984"},"titulo":{"S":"216"},"acciones":{"N":"60"},"fechaCompra":{"S":"04-10-2021"},"estado":{"S":"Activo" } } } },
    { "PutRequest": { "Item": { "id": { "S": "367"},"accionistaID":{"S":"37985"},"titulo":{"S":"228"},"acciones":{"N":"60"},"fechaCompra":{"S":"04-10-2021"},"estado":{"S":"Activo" } } } },
    { "PutRequest": { "Item": { "id": { "S": "368"},"accionistaID":{"S":"37987"},"titulo":{"S":"240"},"acciones":{"N":"60"},"fechaCompra":{"S":"04-10-2021"},"estado":{"S":"Activo" } } } },
    { "PutRequest": { "Item": { "id": { "S": "369"},"accionistaID":{"S":"37988"},"titulo":{"S":"241"},"acciones":{"N":"60"},"fechaCompra":{"S":"04-10-2021"},"estado":{"S":"Activo" } } } },
    { "PutRequest": { "Item": { "id": { "S": "370"},"accionistaID":{"S":"37989"},"titulo":{"S":"249"},"acciones":{"N":"60"},"fechaCompra":{"S":"04-10-2021"},"estado":{"S":"Activo" } } } },
    { "PutRequest": { "Item": { "id": { "S": "371"},"accionistaID":{"S":"37990"},"titulo":{"S":"272"},"acciones":{"N":"60"},"fechaCompra":{"S":"04-10-2021"},"estado":{"S":"Activo" } } } },
    { "PutRequest": { "Item": { "id": { "S": "372"},"accionistaID":{"S":"37991"},"titulo":{"S":"273"},"acciones":{"N":"60"},"fechaCompra":{"S":"04-10-2021"},"estado":{"S":"Activo" } } } },
    { "PutRequest": { "Item": { "id": { "S": "373"},"accionistaID":{"S":"37992"},"titulo":{"S":"274"},"acciones":{"N":"60"},"fechaCompra":{"S":"04-10-2021"},"estado":{"S":"Activo" } } } },
    { "PutRequest": { "Item": { "id": { "S": "374"},"accionistaID":{"S":"37993"},"titulo":{"S":"275"},"acciones":{"N":"60"},"fechaCompra":{"S":"04-10-2021"},"estado":{"S":"Activo" } } } },
    { "PutRequest": { "Item": { "id": { "S": "375"},"accionistaID":{"S":"37994"},"titulo":{"S":"284"},"acciones":{"N":"60"},"fechaCompra":{"S":"04-10-2021"},"estado":{"S":"Activo" } } } } ] }
    